<?xml version="1.0" encoding="utf-8"?>
<!-- edited with XMLSPY v2004 rel. 2 U (http://www.xmlspy.com) by IMC (IMCGames Co., Ltd) -->
<ToolSkill>
	<Skill Name="Catagnan_Transform">
		<MainSkl JumpFlee="NO" MSPDToUsePos="0" ScrLock="None">
			<HitList>
				<Frame Angle="0" AniTime="99999" Dist="0" ForceATK="0" HitCount="1" Length="30" PosType="0" RandDist="0" RandomPerHit="0" RotAngle="0" SklAngle="0.17453292" TermMax="0" TermMin="0" Time="99799" Type="FAN" Width="30"/>
			</HitList>
			<EtcList>
				<Scp Client="YES" Scp="MONSKL_C_PLAY_ANIM" Time="0" UseSleep="NO">
					<Str Str="skl_catagnan"/>
					<Num Num="1"/>
					<Num Num="1"/>
					<Num Num="0"/>
				</Scp>
				<Scp Client="YES" Scp="C_SOUND" Time="0" UseSleep="NO">
					<Str Str="skl_fgt_champion"/>
				</Scp>
				<Scp Client="YES" Scp="C_SOUND" Time="200" UseSleep="NO">
					<Str Str="skl_eff_pistol_cat_shot"/>
				</Scp>
				<Scp Client="YES" Scp="C_SOUND" Time="1000" UseSleep="NO">
					<Str Str="skl_fgt_light_cast_2"/>
				</Scp>
				<Scp Client="NO" Scp="SKL_BUFF" Time="0" UseSleep="NO">
					<Str Str="ITEM_BUFF_Catagnan_Transform"/>
					<Num Num="1"/>
					<Num Num="0"/>
					<Num Num="900000"/>
					<Num Num="1"/>
					<Num Num="100"/>
					<Num Num="0"/>
				</Scp>
				<Scp Client="NO" Scp="SKL_BUFF" Time="0" UseSleep="NO">
					<Str Str="ITEM_BUFF_Catagnan_Transform_Rapier"/>
					<Num Num="1"/>
					<Num Num="0"/>
					<Num Num="3000"/>
					<Num Num="1"/>
					<Num Num="100"/>
					<Num Num="0"/>
				</Scp>
			</EtcList>
		</MainSkl>
	</Skill>
</ToolSkill>
