<?xml version="1.0" encoding="utf-8"?>
<!-- edited with XMLSPY v2004 rel. 2 U (http://www.xmlspy.com) by IMC (IMCGames Co., Ltd) -->
<ToolSkill>
    <Skill Name="Mon_ep12_aklaspetal_sword_Skill_1">
        <MainSkl ScrLock="None" JumpFlee="NO" MSPDToUsePos="0">
            <HitList>
                <Frame Type="FAN" Time="300" HitCount="1" TermMin="0" TermMax="0" PosType="0" Dist="0" RandDist="0" RandomPerHit="0" Angle="0" Width="30" Length="35" SklAngle="0.52359879" AniTime="500" RotAngle="0" ForceATK="0"/>
            </HitList>
            <EtcList>
                <Anim Time="0" Anim="atk" Speed="1"/>
            </EtcList>
        </MainSkl>
    </Skill>
    <Skill Name="Mon_ep12_aklaspetal_sword_Skill_2">
        <MainSkl ScrLock="None" JumpFlee="NO" MSPDToUsePos="0">
            <MoveList>
                <Frame Time="500" Dist="1.0799354" Angle="0.06966909" Accel="1" Height="0" MoveType="0" Gravity="600" JumpPower="300"/>
                <Frame Time="800" Dist="28.350706" Angle="-0.012908929" Accel="1" Height="0" MoveType="0" Gravity="600" JumpPower="300"/>
            </MoveList>
            <HitList>
                <Frame Type="SQUARE" Time="450" HitCount="1" TermMin="0" TermMax="0" PosType="0" Dist="0" RandDist="0" RandomPerHit="0" Angle="0" Width="10" Length="50" AniTime="650" RotAngle="0" ForceATK="0"/>
            </HitList>
            <EtcList>
                <Anim Time="0" Anim="skl" Speed="1"/>
            </EtcList>
        </MainSkl>
    </Skill>
    <Skill Name="Mon_ep12_Pawnta_Skill_1">
        <MainSkl ScrLock="None" JumpFlee="NO" MSPDToUsePos="0">
            <HitList>
                <Frame Type="FAN" Time="300" HitCount="2" TermMin="500" TermMax="0" PosType="0" Dist="0" RandDist="0" RandomPerHit="0" Angle="0" Width="30" Length="40" SklAngle="0.52359879" AniTime="500" RotAngle="0" ForceATK="0"/>
            </HitList>
            <EtcList>
                <Anim Time="0" Anim="atk" Speed="1"/>
            </EtcList>
        </MainSkl>
    </Skill>
    <Skill Name="Mon_ep12_Living_armor_Skill_2">
        <MainSkl ScrLock="None" JumpFlee="NO" MSPDToUsePos="0">
            <MoveList>
                <Frame Time="1000" Dist="0.81914139" Angle="2.3569598" Accel="1" Height="0" MoveType="0" Gravity="600" JumpPower="300"/>
                <Frame Time="1500" Dist="72.41848" Angle="0.0003968089" Accel="1" Height="0" MoveType="0" Gravity="600" JumpPower="300"/>
            </MoveList>
            <HitList>
                <Frame Type="CIRCLE" Time="9999" HitCount="1" TermMin="0" TermMax="0" PosType="0" Dist="0" RandDist="0" RandomPerHit="0" Angle="0" Width="30" Length="30" SklAngle="0.17453292" AniTime="10199" RotAngle="0" ForceATK="0"/>
            </HitList>
            <EtcList>
                <Anim Time="0" Anim="skl" Speed="1"/>
                <Scp Scp="EFT_AND_HIT_ARROW" Client="NO" UseSleep="YES" Time="0">
                    <Pos Angle="0" Dist="0"/>
                    <Pos Angle="0" Dist="100"/>
                    <Str_Arg Str="None" Arg="1"/>
                    <Num Num="25"/>
                    <Num Num="0.0099999998"/>
                    <Num Num="1"/>
                    <Num Num="1000"/>
                    <Str_Arg Str="None" Arg="1"/>
                    <Num Num="45"/>
                    <Num Num="0"/>
                    <Num Num="0"/>
                    <Num Num="25"/>
                    <Num Num="0.1"/>
                    <Num Num="1"/>
                    <Num Num="1000"/>
                    <Num Num="1"/>
                    <Num Num="0"/>
                    <Num Num="0"/>
                    <Num Num="100"/>
                </Scp>
            </EtcList>
        </MainSkl>
    </Skill>
    <Skill Name="Mon_ep12_Living_armor_Skill_1">
        <MainSkl ScrLock="None" JumpFlee="NO" MSPDToUsePos="0">
            <HitList>
                <Frame Type="FAN" Time="250" HitCount="1" TermMin="0" TermMax="0" PosType="0" Dist="0" RandDist="0" RandomPerHit="0" Angle="0" Width="30" Length="45" SklAngle="0.52359879" AniTime="450" RotAngle="0" ForceATK="0"/>
            </HitList>
            <EtcList>
                <Anim Time="0" Anim="atk" Speed="1"/>
            </EtcList>
        </MainSkl>
    </Skill>
    <Skill Name="Mon_ep12_Nuo_twinsword_Skill_2">
        <MainSkl ScrLock="None" JumpFlee="NO" MSPDToUsePos="0">
            <HitList>
                <Frame Type="FAN" Time="300" HitCount="1" TermMin="0" TermMax="0" PosType="0" Dist="0" RandDist="0" RandomPerHit="0" Angle="0" Width="30" Length="35" SklAngle="0.52359879" AniTime="500" RotAngle="0" ForceATK="0"/>
                <Frame Type="FAN" Time="600" HitCount="1" TermMin="0" TermMax="0" PosType="0" Dist="0" RandDist="0" RandomPerHit="0" Angle="0" Width="30" Length="35" SklAngle="0.52359879" AniTime="800" RotAngle="0" ForceATK="0"/>
                <Frame Type="FAN" Time="900" HitCount="1" TermMin="0" TermMax="0" PosType="0" Dist="0" RandDist="0" RandomPerHit="0" Angle="0" Width="30" Length="35" SklAngle="0.52359879" AniTime="1100" RotAngle="0" ForceATK="0"/>
            </HitList>
            <EtcList>
                <Anim Time="0" Anim="skl" Speed="1"/>
            </EtcList>
        </MainSkl>
    </Skill>
    <Skill Name="Mon_ep12_Nuo_twinsword_Skill_1">
        <MainSkl ScrLock="None" JumpFlee="NO" MSPDToUsePos="0">
            <HitList>
                <Frame Type="FAN" Time="200" HitCount="1" TermMin="0" TermMax="0" PosType="0" Dist="0" RandDist="0" RandomPerHit="0" Angle="0" Width="30" Length="35" SklAngle="0.52359879" AniTime="400" RotAngle="0" ForceATK="0"/>
                <Frame Type="FAN" Time="500" HitCount="1" TermMin="0" TermMax="0" PosType="0" Dist="0" RandDist="0" RandomPerHit="0" Angle="0" Width="30" Length="35" SklAngle="0.52359879" AniTime="700" RotAngle="0" ForceATK="0"/>
            </HitList>
            <EtcList>
                <Anim Time="0" Anim="atk" Speed="1"/>
            </EtcList>
        </MainSkl>
    </Skill>
    <Skill Name="Mon_ep12_Nuka_shield_Skill_2">
        <MainSkl ScrLock="None" JumpFlee="NO" MSPDToUsePos="0">
            <HitList>
                <Frame Type="FAN" Time="100" HitCount="1" TermMin="0" TermMax="0" PosType="0" Dist="0" RandDist="0" RandomPerHit="0" Angle="0" Width="30" Length="35" SklAngle="0.52359879" AniTime="300" RotAngle="0" ForceATK="0"/>
            </HitList>
            <EtcList>
                <Anim Time="0" Anim="skl" Speed="1"/>
            </EtcList>
        </MainSkl>
    </Skill>
    <Skill Name="Mon_ep12_Nuka_shield_Skill_1">
        <MainSkl ScrLock="None" JumpFlee="NO" MSPDToUsePos="0">
            <HitList>
                <Frame Type="SQUARE" Time="100" HitCount="1" TermMin="0" TermMax="0" PosType="0" Dist="0" RandDist="0" RandomPerHit="0" Angle="0" Width="10" Length="40" SklAngle="0.52359879" AniTime="300" RotAngle="0" ForceATK="0"/>
            </HitList>
            <EtcList>
                <Anim Time="0" Anim="atk" Speed="1"/>
            </EtcList>
        </MainSkl>
    </Skill>
    <Skill Name="Mon_ep12_Orc_flag_Skill_2">
        <MainSkl ScrLock="None" JumpFlee="NO" MSPDToUsePos="0">
            <HitList>
                <Frame Type="FAN" Time="9999" HitCount="1" TermMin="0" TermMax="0" PosType="0" Dist="0" RandDist="0" RandomPerHit="0" Angle="0" Width="30" Length="30" SklAngle="0.17453292" AniTime="10199" RotAngle="0" ForceATK="0"/>
            </HitList>
            <EtcList>
                <Anim Time="0" Anim="skl" Speed="1"/>
                <Scp Scp="C_EFFECT_ATTACH" Client="YES" UseSleep="NO" Time="800">
                    <Str_Arg Str="F_warrior_provoke_shot_lineup2" Arg="1"/>
                    <Num Num="2"/>
                    <Pos Angle="0" Dist="0"/>
                    <Num Num="0"/>
                    <Num Num="-1"/>
                </Scp>
                <Scp Scp="SKL_BUFF" Client="NO" UseSleep="NO" Time="800">
                    <Str Str="ATKUP"/>
                    <Num Num="1"/>
                    <Num Num="100"/>
                    <Num Num="30000"/>
                    <Num Num="1"/>
                    <Num Num="100"/>
                    <Num Num="0"/>
                </Scp>
                <Scp Scp="C_EFFECT_DETACH" Client="YES" UseSleep="NO" Time="1000">
                    <Str_Arg Str="F_warrior_provoke_shot_lineup2" Arg="1"/>
                    <Num Num="0.5"/>
                </Scp>
            </EtcList>
        </MainSkl>
    </Skill>
    <Skill Name="Mon_ep12_Orc_flag_Skill_1">
        <MainSkl ScrLock="None" JumpFlee="NO" MSPDToUsePos="0">
            <HitList>
                <Frame Type="SQUARE" Time="600" HitCount="1" TermMin="0" TermMax="0" PosType="0" Dist="0" RandDist="0" RandomPerHit="0" Angle="0" Width="10" Length="50" SklAngle="0.17453292" AniTime="800" RotAngle="0" ForceATK="0"/>
            </HitList>
            <EtcList>
                <Anim Time="0" Anim="atk" Speed="1"/>
            </EtcList>
        </MainSkl>
    </Skill>
    <Skill Name="Mon_ep12_Orc_cannon_Skill_2">
        <MainSkl ScrLock="None" JumpFlee="NO" MSPDToUsePos="0">
            <HitList>
                <Frame Type="FAN" Time="9999" HitCount="1" TermMin="0" TermMax="0" PosType="0" Dist="0" RandDist="0" RandomPerHit="0" Angle="0" Width="30" Length="30" SklAngle="0.17453292" AniTime="10199" RotAngle="0" ForceATK="0"/>
            </HitList>
            <EtcList>
                <Anim Time="0" Anim="skl" Speed="1"/>
                <Scp Scp="SKL_SET_TARGET_CIRCLE" Client="NO" UseSleep="NO" Time="0">
                    <Pos Angle="0" Dist="0"/>
                    <Num Num="100"/>
                    <Num Num="5"/>
                    <Num Num="2"/>
                    <Num Num="0"/>
                    <Num Num="1"/>
                    <Num Num="1"/>
                    <Num Num="0"/>
                    <Num Num="1"/>
                </Scp>
                <Scp Scp="C_EFFECT" Client="YES" UseSleep="NO" Time="500">
                    <Str_Arg Str="I_spread_in009_violet2" Arg="1"/>
                    <Str Str="Dummy_weapon02"/>
                    <Num Num="0.2"/>
                </Scp>
                <Scp Scp="MSL_THROW_SYNC" Client="NO" UseSleep="YES" TooltipScp="TOOLTIP_MSL_THROW" Time="1250">
                    <Str_Arg Str="I_archer_canon_force3#Dummy_weapon02" Arg="1"/>
                    <Str_Arg Str="F_explosion128_dark_burst" Arg="2"/>
                    <Str_Arg Str="I_force003_green" Arg="1"/>
                    <Pos Angle="0" Dist="0" PosType="1"/>
                    <Num Num="25"/>
                    <Num Num="1"/>
                    <Num Num="0"/>
                    <Num Num="300"/>
                    <Num Num="1"/>
                    <Num Num="1000"/>
                    <Num Num="1"/>
                    <Num Num="0"/>
                    <Str_Arg Str="None" Arg="1"/>
                    <Num Num="0"/>
                    <Num Num="0"/>
                    <Num Num="0"/>
                    <Num Num="1"/>
                    <Num Num="0"/>
                </Scp>
            </EtcList>
        </MainSkl>
    </Skill>
    <Skill Name="Mon_ep12_Orc_cannon_Skill_1">
        <MainSkl ScrLock="None" JumpFlee="NO" MSPDToUsePos="0">
            <HitList>
                <Frame Type="SQUARE" Time="500" HitCount="1" TermMin="0" TermMax="0" PosType="0" Dist="0" RandDist="0" RandomPerHit="0" Angle="0" Width="10" Length="100" SklAngle="0.17453292" AniTime="700" RotAngle="0" ForceATK="1"/>
            </HitList>
            <EtcList>
                <Anim Time="0" Anim="atk" Speed="1"/>
                <Scp Scp="C_FORCE_EFT" Client="YES_Time" UseSleep="NO" Time="500">
                    <Str_Arg Str="I_archer_canon_force_forge#Dummy_weapon02" Arg="1"/>
                    <Str Str="arrow_cast"/>
                    <Str_Arg Str="I_explosion002_green" Arg="1"/>
                    <Str Str="arrow_blow"/>
                    <Str Str="SLOW"/>
                    <Num Num="300"/>
                    <Num Num="1"/>
                    <Num Num="0"/>
                    <Angle_Abs Angle="0"/>
                    <Num Num="0"/>
                    <Num Num="5"/>
                    <Num Num="10"/>
                    <Num Num="0"/>
                    <Num Num="1"/>
                    <Num Num="1"/>
                    <Str Str="None"/>
                    <PosDist Angle="0" Dist="0"/>
                    <Num Num="0"/>
                </Scp>
            </EtcList>
        </MainSkl>
    </Skill>
    <Skill Name="Mon_ep12_Orc_leader_Skill_2">
        <MainSkl ScrLock="None" JumpFlee="NO" MSPDToUsePos="0">
            <HitList>
                <Frame Type="SQUARE" Time="1000" HitCount="1" TermMin="0" TermMax="0" PosType="0" Dist="0" RandDist="0" RandomPerHit="0" Angle="0" Width="15" Length="80" SklAngle="0.17453292" AniTime="1200" RotAngle="0" ForceATK="0"/>
            </HitList>
            <EtcList>
                <Anim Time="0" Anim="skl" Speed="1"/>
                <Scp Scp="EFT_AND_HIT" Client="NO" UseSleep="YES" TooltipScp="TOOLTIP_EFT_AND_HIT" Time="1500">
                    <Pos Angle="0" Dist="70"/>
                    <Str_Arg Str="None" Arg="1"/>
                    <Num Num="0"/>
                    <Str_Arg Str="F_burstup048_fire_3" Arg="2"/>
                    <Num Num="30"/>
                    <Num Num="100"/>
                    <Num Num="0"/>
                    <Num Num="1"/>
                    <Num Num="1000"/>
                    <Str_Arg Str="None" Arg="1"/>
                    <Str Str="None"/>
                    <Num Num="1"/>
                    <Num Num="0"/>
                    <Num Num="0"/>
                </Scp>
            </EtcList>
        </MainSkl>
    </Skill>
    <Skill Name="Mon_ep12_Orc_leader_Skill_1">
        <MainSkl ScrLock="None" JumpFlee="NO" MSPDToUsePos="0">
            <HitList>
                <Frame Type="FAN" Time="650" HitCount="1" TermMin="0" TermMax="0" PosType="0" Dist="0" RandDist="0" RandomPerHit="0" Angle="0" Width="30" Length="60" SklAngle="0.69813174" AniTime="850" RotAngle="0" ForceATK="0"/>
            </HitList>
            <EtcList>
                <Anim Time="0" Anim="atk" Speed="1"/>
            </EtcList>
        </MainSkl>
    </Skill>
    <Skill Name="Mon_ep12_Orc_shield_Skill_2">
        <MainSkl ScrLock="None" JumpFlee="NO" MSPDToUsePos="0">
            <HitList>
                <Frame Type="FAN" Time="200" HitCount="1" TermMin="0" TermMax="0" PosType="0" Dist="0" RandDist="0" RandomPerHit="0" Angle="0" Width="30" Length="40" SklAngle="0.52359879" AniTime="400" RotAngle="0" ForceATK="0"/>
                <Frame Type="FAN" Time="900" HitCount="1" TermMin="0" TermMax="0" PosType="0" Dist="0" RandDist="0" RandomPerHit="0" Angle="0" Width="30" Length="45" SklAngle="0.52359879" AniTime="1100" RotAngle="0" ForceATK="0"/>
            </HitList>
            <EtcList>
                <Anim Time="0" Anim="skl" Speed="1"/>
            </EtcList>
        </MainSkl>
    </Skill>
    <Skill Name="Mon_ep12_Orc_shield_Skill_1">
        <MainSkl ScrLock="None" JumpFlee="NO" MSPDToUsePos="0">
            <MoveList>
                <Frame Time="600" Dist="3.2486415" Angle="-1.0445274" Accel="1" Height="0" MoveType="0" Gravity="600" JumpPower="300"/>
                <Frame Time="800" Dist="16.25342" Angle="-0.12057583" Accel="1" Height="0" MoveType="0" Gravity="600" JumpPower="300"/>
            </MoveList>
            <HitList>
                <Frame Type="FAN" Time="200" HitCount="1" TermMin="0" TermMax="0" PosType="0" Dist="0" RandDist="0" RandomPerHit="0" Angle="0" Width="30" Length="40" SklAngle="0.52359879" AniTime="400" RotAngle="0" ForceATK="0"/>
                <Frame Type="FAN" Time="500" HitCount="1" TermMin="0" TermMax="0" PosType="0" Dist="0" RandDist="0" RandomPerHit="0" Angle="0" Width="30" Length="40" SklAngle="0.52359879" AniTime="700" RotAngle="0" ForceATK="0"/>
            </HitList>
            <EtcList>
                <Anim Time="0" Anim="atk" Speed="1"/>
            </EtcList>
        </MainSkl>
    </Skill>
    <Skill Name="Mon_ep12_Orc_double_axe_Skill_2">
        <MainSkl ScrLock="None" JumpFlee="NO" MSPDToUsePos="0">
            <HitList>
                <Frame Type="FAN" Time="500" HitCount="1" TermMin="0" TermMax="0" PosType="0" Dist="0" RandDist="0" RandomPerHit="0" Angle="0" Width="30" Length="30" SklAngle="0.52359879" AniTime="700" RotAngle="0" ForceATK="0"/>
            </HitList>
            <EtcList>
                <Anim Time="0" Anim="skl" Speed="1"/>
                <Scp Scp="EFT_AND_HIT_ARROW" Client="NO" UseSleep="YES" Time="1000">
                    <Pos Angle="0" Dist="10"/>
                    <Pos Angle="0" Dist="100"/>
                    <Str_Arg Str="None" Arg="1"/>
                    <Num Num="30"/>
                    <Num Num="0.1"/>
                    <Num Num="1"/>
                    <Num Num="0"/>
                    <Str_Arg Str="F_burstup022_smoke_s" Arg="0.40000001"/>
                    <Num Num="20"/>
                    <Num Num="100"/>
                    <Num Num="0"/>
                    <Num Num="20"/>
                    <Num Num="0.1"/>
                    <Num Num="1"/>
                    <Num Num="1000"/>
                    <Num Num="1"/>
                    <Num Num="0"/>
                </Scp>
            </EtcList>
        </MainSkl>
    </Skill>
    <Skill Name="Mon_ep12_Orc_double_axe_Skill_1">
        <MainSkl ScrLock="None" JumpFlee="NO" MSPDToUsePos="0">
            <HitList>
                <Frame Type="FAN" Time="150" HitCount="1" TermMin="0" TermMax="0" PosType="0" Dist="0" RandDist="0" RandomPerHit="0" Angle="0" Width="30" Length="40" SklAngle="0.52359879" AniTime="350" RotAngle="0" ForceATK="0"/>
                <Frame Type="FAN" Time="800" HitCount="1" TermMin="0" TermMax="0" PosType="0" Dist="0" RandDist="0" RandomPerHit="0" Angle="0" Width="30" Length="40" SklAngle="0.52359879" AniTime="1000" RotAngle="0" ForceATK="0"/>
            </HitList>
            <EtcList>
                <Anim Time="0" Anim="atk" Speed="1"/>
            </EtcList>
        </MainSkl>
    </Skill>
    <Skill Name="Mon_ep12_Pawnta_Skill_2">
        <MainSkl ScrLock="None" JumpFlee="NO" MSPDToUsePos="0">
            <MoveList>
                <Frame Time="1000" Dist="1.7151493" Angle="0.12097056" Accel="1" Height="0" MoveType="0" Gravity="600" JumpPower="300"/>
                <Frame Time="1200" Dist="27.362068" Angle="0.02093607" Accel="1" Height="0" MoveType="0" Gravity="600" JumpPower="300"/>
            </MoveList>
            <HitList>
                <Frame Type="FAN" Time="300" HitCount="2" TermMin="0" TermMax="0" PosType="0" Dist="0" RandDist="0" RandomPerHit="0" Angle="0" Width="30" Length="40" SklAngle="0.52359879" AniTime="500" RotAngle="0" ForceATK="0"/>
            </HitList>
            <EtcList>
                <Anim Time="0" Anim="skl" Speed="1"/>
                <Scp Scp="EFT_AND_HIT" Client="NO" UseSleep="YES" TooltipScp="TOOLTIP_EFT_AND_HIT" Time="1300">
                    <Pos Angle="0" Dist="40"/>
                    <Str_Arg Str="None" Arg="1"/>
                    <Num Num="0"/>
                    <Str_Arg Str="None" Arg="1"/>
                    <Num Num="25"/>
                    <Num Num="100"/>
                    <Num Num="0"/>
                    <Num Num="1"/>
                    <Num Num="1000"/>
                    <Str_Arg Str="None" Arg="1"/>
                    <Str Str="None"/>
                    <Num Num="1"/>
                    <Num Num="0"/>
                    <Num Num="0"/>
                </Scp>
            </EtcList>
        </MainSkl>
    </Skill>
    <Skill Name="Mon_ep12_viskal_Skill_1">
        <MainSkl ScrLock="None" JumpFlee="NO" MSPDToUsePos="0">
            <HitList>
                <Frame Type="FAN" Time="600" HitCount="1" TermMin="0" TermMax="0" PosType="0" Dist="0" RandDist="0" RandomPerHit="0" Angle="0" Width="60" Length="60" SklAngle="0.52359879" AniTime="800" RotAngle="0" ForceATK="0"/>
            </HitList>
            <EtcList>
                <Anim Time="0" Anim="atk" Speed="1"/>
            </EtcList>
        </MainSkl>
    </Skill>
    <Skill Name="Mon_ep12_viskal_Skill_2">
        <MainSkl ScrLock="None" JumpFlee="NO" MSPDToUsePos="0">
            <HitList>
                <Frame Type="SQUARE" Time="9999" HitCount="1" TermMin="0" TermMax="0" PosType="0" Dist="0" RandDist="0" RandomPerHit="0" Angle="0" Width="10" Length="40" AniTime="10199" RotAngle="0" ForceATK="0"/>
            </HitList>
            <EtcList>
                <Anim Time="0" Anim="skl" Speed="1"/>
                <Scp Scp="EFT_AND_HIT_ARROW" Client="NO" UseSleep="YES" Time="1000">
                    <Pos Angle="-1.66706" Dist="21.834303"/>
                    <Pos Angle="0" Dist="120"/>
                    <Str_Arg Str="F_sys_arrow_monster##0.5" Arg="0.60000002"/>
                    <Num Num="25"/>
                    <Num Num="0.1"/>
                    <Num Num="0.5"/>
                    <Num Num="1000"/>
                    <Str_Arg Str="I_explosion002_green" Arg="1"/>
                    <Num Num="20"/>
                    <Num Num="100"/>
                    <Num Num="0"/>
                    <Num Num="20"/>
                    <Num Num="0.1"/>
                    <Num Num="1"/>
                    <Num Num="1000"/>
                    <Num Num="1"/>
                    <Num Num="0"/>
                    <Num Num="0"/>
                    <Num Num="100"/>
                </Scp>
            </EtcList>
        </MainSkl>
    </Skill>
    <Skill Name="Mon_ep12_vilktis_Skill_1">
        <MainSkl ScrLock="None" JumpFlee="NO" MSPDToUsePos="0">
            <HitList>
                <Frame Type="FAN" Time="300" HitCount="2" TermMin="500" TermMax="0" PosType="0" Dist="0" RandDist="0" RandomPerHit="0" Angle="0" Width="30" Length="50" SklAngle="0.52359879" AniTime="500" RotAngle="0" ForceATK="0"/>
            </HitList>
            <EtcList>
                <Anim Time="0" Anim="atk" Speed="1"/>
            </EtcList>
        </MainSkl>
    </Skill>
    <Skill Name="Mon_ep12_vilktis_Skill_2">
        <MainSkl ScrLock="None" JumpFlee="NO" MSPDToUsePos="0">
            <HitList>
                <Frame Type="SQUARE" Time="300" HitCount="1" TermMin="0" TermMax="0" PosType="0" Dist="0" RandDist="0" RandomPerHit="0" Angle="0" Width="10" Length="60" AniTime="500" RotAngle="0" ForceATK="0"/>
                <Frame Type="SQUARE" Time="1000" HitCount="1" TermMin="0" TermMax="0" PosType="0" Dist="0" RandDist="0" RandomPerHit="0" Angle="0" Width="10" Length="60" AniTime="1200" RotAngle="0" ForceATK="0"/>
            </HitList>
            <EtcList>
                <Anim Time="0" Anim="skl" Speed="1"/>
            </EtcList>
        </MainSkl>
    </Skill>
    <Skill Name="Mon_ep12_trampled_Skill_1">
        <MainSkl ScrLock="None" JumpFlee="NO" MSPDToUsePos="0">
            <HitList>
                <Frame Type="FAN" Time="300" HitCount="1" TermMin="0" TermMax="0" PosType="0" Dist="0" RandDist="0" RandomPerHit="0" Angle="0" Width="30" Length="60" SklAngle="0.52359879" AniTime="500" RotAngle="0" ForceATK="0"/>
            </HitList>
            <EtcList>
                <Anim Time="0" Anim="atk" Speed="1"/>
            </EtcList>
        </MainSkl>
    </Skill>
    <Skill Name="Mon_ep12_trampled_Skill_2">
        <MainSkl ScrLock="None" JumpFlee="NO" MSPDToUsePos="0">
            <HitList>
                <Frame Type="SQUARE" Time="9999" HitCount="1" TermMin="0" TermMax="0" PosType="0" Dist="0" RandDist="0" RandomPerHit="0" Angle="0" AniTime="10199" RotAngle="0" ForceATK="0"/>
            </HitList>
            <EtcList>
                <Anim Time="0" Anim="skl" Speed="1"/>
                <Scp Scp="EFT_AND_HIT_ARROW" Client="NO" UseSleep="YES" Time="0">
                    <Pos Angle="0" Dist="10"/>
                    <Pos Angle="0" Dist="100"/>
                    <Str_Arg Str="F_sys_arrow_monster" Arg="0.5"/>
                    <Num Num="25"/>
                    <Num Num="0.0099999998"/>
                    <Num Num="0.5"/>
                    <Num Num="800"/>
                    <Str_Arg Str="I_explosion002_green" Arg="1"/>
                    <Num Num="20"/>
                    <Num Num="100"/>
                    <Num Num="0"/>
                    <Num Num="20"/>
                    <Num Num="0.1"/>
                    <Num Num="1"/>
                    <Num Num="1000"/>
                    <Num Num="1"/>
                    <Num Num="0"/>
                    <Num Num="0"/>
                    <Num Num="100"/>
                </Scp>
            </EtcList>
        </MainSkl>
    </Skill>
    <Skill Name="Mon_ep12_castle_troll_Skill_1">
        <MainSkl ScrLock="None" JumpFlee="NO" MSPDToUsePos="0">
            <HitList>
                <Frame Type="FAN" Time="600" HitCount="1" TermMin="0" TermMax="0" PosType="0" Dist="0" RandDist="0" RandomPerHit="0" Angle="0" Width="30" Length="50" SklAngle="0.52359879" AniTime="800" RotAngle="0" ForceATK="0"/>
            </HitList>
            <EtcList>
                <Anim Time="0" Anim="atk" Speed="1"/>
                <Scp Scp="C_SOUND" Client="YES" UseSleep="NO" Time="100">
                    <Str Str="mon_saurman_warrior_atk1_cast"/>
                </Scp>
                <Scp Scp="C_SOUND" Client="YES" UseSleep="NO" Time="550">
                    <Str Str="mon_saurman_warrior_atk1_shot"/>
                </Scp>
            </EtcList>
        </MainSkl>
    </Skill>
    <Skill Name="Mon_ep12_castle_troll_Skill_2">
        <MainSkl ScrLock="None" JumpFlee="NO" MSPDToUsePos="0">
            <MoveList>
                <Frame Time="600" Dist="0.93399847" Angle="-0.15401326" Accel="1" Height="0" MoveType="0" Gravity="600" JumpPower="300"/>
                <Frame Time="900" Dist="24.122034" Angle="-0.022430276" Accel="1" Height="0" MoveType="0" Gravity="600" JumpPower="300"/>
            </MoveList>
            <HitList>
                <Frame Type="SQUARE" Time="500" HitCount="1" TermMin="0" TermMax="0" PosType="0" Dist="0" RandDist="0" RandomPerHit="0" Angle="0" Width="15" Length="55" AniTime="700" RotAngle="0" ForceATK="0"/>
            </HitList>
            <EtcList>
                <Anim Time="0" Anim="skl" Speed="1"/>
            </EtcList>
        </MainSkl>
    </Skill>
    <Skill Name="Mon_ep12_castle_goblin_archer_Skill_1">
        <MainSkl ScrLock="None" JumpFlee="NO" MSPDToUsePos="0">
            <HitList>
                <Frame Type="SQUARE" Time="400" HitCount="1" TermMin="0" TermMax="0" PosType="0" Dist="0" RandDist="0" RandomPerHit="0" Angle="0" Width="10" Length="120" SklAngle="0.52359879" AniTime="600" RotAngle="0" ForceATK="0"/>
            </HitList>
            <EtcList>
                <Anim Time="0" Anim="atk" Speed="1"/>
                <Scp Scp="C_FORCE_EFT" Client="YES_Time" UseSleep="NO" Time="500">
                    <Str_Arg Str="I_arrow009#Dummy_bow" Arg="0.69999999"/>
                    <Str Str="arrow_cast"/>
                    <Str_Arg Str="None" Arg="1"/>
                    <Str Str="arrow_blow"/>
                    <Str Str="SLOW"/>
                    <Num Num="500"/>
                    <Num Num="1"/>
                    <Num Num="0"/>
                    <Angle_Abs Angle="0"/>
                    <Num Num="0"/>
                    <Num Num="5"/>
                    <Num Num="0"/>
                    <Num Num="0"/>
                    <Num Num="1"/>
                </Scp>
            </EtcList>
        </MainSkl>
    </Skill>
    <Skill Name="Mon_ep12_castle_goblin_archer_Skill_2">
        <MainSkl ScrLock="None" JumpFlee="NO" MSPDToUsePos="0">
            <HitList>
                <Frame Type="SQUARE" Time="500" HitCount="1" TermMin="0" TermMax="0" PosType="0" Dist="0" RandDist="0" RandomPerHit="0" Angle="0" Width="10" Length="100" AniTime="700" RotAngle="0" ForceATK="0"/>
                <Frame Type="SQUARE" Time="650" HitCount="1" TermMin="0" TermMax="0" PosType="0" Dist="0" RandDist="0" RandomPerHit="0" Angle="0" Width="10" Length="100" AniTime="850" RotAngle="-0.34906587" ForceATK="0"/>
                <Frame Type="SQUARE" Time="800" HitCount="1" TermMin="0" TermMax="0" PosType="0" Dist="0" RandDist="0" RandomPerHit="0" Angle="0" Width="10" Length="100" AniTime="1000" RotAngle="0.34906587" ForceATK="0"/>
                <Frame Type="SQUARE" Time="950" HitCount="1" TermMin="0" TermMax="0" PosType="0" Dist="0" RandDist="0" RandomPerHit="0" Angle="0" Width="10" Length="100" AniTime="1150" RotAngle="0.52359879" ForceATK="0"/>
            </HitList>
            <EtcList>
                <Anim Time="0" Anim="skl" Speed="1"/>
                <Scp Scp="C_FORCE_EFT" Client="YES_Time" UseSleep="NO" Time="700">
                    <Str_Arg Str="I_arrow009#Dummy_bow" Arg="0.69999999"/>
                    <Str Str="arrow_cast"/>
                    <Str_Arg Str="None" Arg="1"/>
                    <Str Str="arrow_blow"/>
                    <Str Str="SLOW"/>
                    <Num Num="500"/>
                    <Num Num="1"/>
                    <Num Num="0"/>
                    <Angle_Abs Angle="0"/>
                    <Num Num="0"/>
                    <Num Num="5"/>
                    <Num Num="0"/>
                    <Num Num="0"/>
                    <Num Num="1"/>
                </Scp>
                <Scp Scp="C_FORCE_EFT" Client="YES_Time" UseSleep="NO" Time="850">
                    <Str_Arg Str="I_arrow009#Dummy_bow" Arg="0.69999999"/>
                    <Str Str="arrow_cast"/>
                    <Str_Arg Str="None" Arg="1"/>
                    <Str Str="arrow_blow"/>
                    <Str Str="SLOW"/>
                    <Num Num="500"/>
                    <Num Num="1"/>
                    <Num Num="0"/>
                    <Angle_Abs Angle="0"/>
                    <Num Num="0"/>
                    <Num Num="5"/>
                    <Num Num="0"/>
                    <Num Num="0"/>
                    <Num Num="1"/>
                    <Num Num="1"/>
                </Scp>
                <Scp Scp="C_FORCE_EFT" Client="YES_Time" UseSleep="NO" Time="1000">
                    <Str_Arg Str="I_arrow009#Dummy_bow" Arg="0.69999999"/>
                    <Str Str="arrow_cast"/>
                    <Str_Arg Str="None" Arg="1"/>
                    <Str Str="arrow_blow"/>
                    <Str Str="SLOW"/>
                    <Num Num="500"/>
                    <Num Num="1"/>
                    <Num Num="0"/>
                    <Angle_Abs Angle="0"/>
                    <Num Num="0"/>
                    <Num Num="5"/>
                    <Num Num="0"/>
                    <Num Num="0"/>
                    <Num Num="1"/>
                </Scp>
                <Scp Scp="C_FORCE_EFT" Client="YES_Time" UseSleep="NO" Time="1150">
                    <Str_Arg Str="I_arrow009#Dummy_bow" Arg="0.69999999"/>
                    <Str Str="arrow_cast"/>
                    <Str_Arg Str="None" Arg="1"/>
                    <Str Str="arrow_blow"/>
                    <Str Str="SLOW"/>
                    <Num Num="500"/>
                    <Num Num="1"/>
                    <Num Num="0"/>
                    <Angle_Abs Angle="0"/>
                    <Num Num="0"/>
                    <Num Num="5"/>
                    <Num Num="0"/>
                    <Num Num="0"/>
                    <Num Num="1"/>
                </Scp>
            </EtcList>
        </MainSkl>
    </Skill>
    <Skill Name="Mon_ep12_Orc_glaive_Skill_1">
        <MainSkl ScrLock="None" JumpFlee="NO" MSPDToUsePos="0">
            <HitList>
                <Frame Type="FAN" Time="400" HitCount="1" TermMin="0" TermMax="0" PosType="0" Dist="0" RandDist="0" RandomPerHit="0" Angle="0" Width="30" Length="80" SklAngle="0.52359879" AniTime="600" RotAngle="0" ForceATK="0"/>
            </HitList>
            <EtcList>
                <Anim Time="0" Anim="atk" Speed="1"/>
            </EtcList>
        </MainSkl>
    </Skill>
    <Skill Name="Mon_ep12_Orc_glaive_Skill_2">
        <MainSkl ScrLock="None" JumpFlee="NO" MSPDToUsePos="0">
            <HitList>
                <Frame Type="SQUARE" Time="9999" HitCount="1" TermMin="0" TermMax="0" PosType="0" Dist="0" RandDist="0" RandomPerHit="0" Angle="0" Width="10" Length="40" AniTime="10199" RotAngle="0" ForceATK="0"/>
            </HitList>
            <EtcList>
                <Anim Time="0" Anim="skl" Speed="1"/>
                <Scp Scp="EFT_AND_HIT" Client="NO" UseSleep="YES" TooltipScp="TOOLTIP_EFT_AND_HIT" Time="800">
                    <Pos Angle="0" Dist="50"/>
                    <Str_Arg Str="None" Arg="1"/>
                    <Num Num="0"/>
                    <Str_Arg Str="F_burstup001_blue_light" Arg="1"/>
                    <Num Num="50"/>
                    <Num Num="100"/>
                    <Num Num="0"/>
                    <Num Num="2"/>
                    <Num Num="500"/>
                    <Str_Arg Str="None" Arg="1"/>
                    <Str Str="None"/>
                    <Num Num="1"/>
                    <Num Num="0"/>
                    <Num Num="0"/>
                </Scp>
            </EtcList>
        </MainSkl>
    </Skill>
    <Skill Name="Mon_ep12_Orc_wand_Skill_1">
        <MainSkl ScrLock="None" JumpFlee="NO" MSPDToUsePos="0">
            <HitList>
                <Frame Type="SQUARE" Time="700" HitCount="1" TermMin="0" TermMax="0" PosType="0" Dist="0" RandDist="0" RandomPerHit="0" Angle="0" Width="10" Length="110" SklAngle="0.52359879" AniTime="900" RotAngle="0" ForceATK="0"/>
            </HitList>
            <EtcList>
                <Anim Time="0" Anim="atk" Speed="1"/>
                <Scp Scp="C_FORCE_EFT" Client="YES_Time" UseSleep="NO" Time="700">
                    <Str_Arg Str="I_force002_blue#Bip001 L Hand#1" Arg="1"/>
                    <Str Str="arrow_cast"/>
                    <Str_Arg Str="I_explosion002_green" Arg="1"/>
                    <Str Str="arrow_blow"/>
                    <Str Str="SLOW"/>
                    <Num Num="300"/>
                    <Num Num="1"/>
                    <Num Num="0"/>
                    <Angle_Abs Angle="0"/>
                    <Num Num="0"/>
                    <Num Num="5"/>
                    <Num Num="0"/>
                    <Num Num="0"/>
                    <Num Num="1"/>
                    <Num Num="1"/>
                    <Str Str="None"/>
                    <PosDist Angle="0" Dist="0"/>
                    <Num Num="0"/>
                </Scp>
            </EtcList>
        </MainSkl>
    </Skill>
    <Skill Name="Mon_ep12_Orc_wand_Skill_2">
        <MainSkl ScrLock="None" JumpFlee="NO" MSPDToUsePos="0">
            <HitList>
                <Frame Type="SQUARE" Time="9999" HitCount="1" TermMin="0" TermMax="0" PosType="0" Dist="0" RandDist="0" RandomPerHit="0" Angle="0" AniTime="10199" RotAngle="0" ForceATK="0"/>
            </HitList>
            <EtcList>
                <Anim Time="0" Anim="skl" Speed="1"/>
                <Scp Scp="SKL_SET_TARGET_CIRCLE" Client="NO" UseSleep="NO" Time="0">
                    <Pos Angle="0" Dist="0"/>
                    <Num Num="120"/>
                    <Num Num="20"/>
                    <Num Num="2"/>
                    <Num Num="0"/>
                    <Num Num="1"/>
                    <Num Num="1"/>
                    <Num Num="0"/>
                    <Num Num="1"/>
                </Scp>
                <Scp Scp="EFT_AND_HIT" Client="NO" UseSleep="YES" TooltipScp="TOOLTIP_EFT_AND_HIT" Time="0">
                    <Pos Angle="0" Dist="0" PosType="8"/>
                    <Str_Arg Str="I_smoke045_spread_in#None#0.5" Arg="3"/>
                    <Num Num="1000"/>
                    <Str_Arg Str="F_archer_SiegeBurst_explosion" Arg="0.40000001"/>
                    <Num Num="30"/>
                    <Num Num="100"/>
                    <Num Num="0"/>
                    <Num Num="1"/>
                    <Num Num="1000"/>
                    <Str_Arg Str="None" Arg="1"/>
                    <Str Str="None"/>
                    <Num Num="1"/>
                    <Num Num="0"/>
                    <Num Num="0"/>
                </Scp>
            </EtcList>
        </MainSkl>
    </Skill>
    <Skill Name="Mon_ep12_Wolf_leader_Skill_1">
        <MainSkl ScrLock="None" JumpFlee="NO" MSPDToUsePos="0">
            <HitList>
                <Frame Type="CIRCLE" Time="500" HitCount="1" TermMin="0" TermMax="0" PosType="0" Dist="0" RandDist="0" RandomPerHit="0" Angle="0" Width="30" Length="45" SklAngle="0.52359879" AniTime="700" RotAngle="0" ForceATK="0"/>
            </HitList>
            <EtcList>
                <Anim Time="0" Anim="atk" Speed="1"/>
            </EtcList>
        </MainSkl>
    </Skill>
    <Skill Name="Mon_ep12_Wolf_leader_Skill_2">
        <MainSkl ScrLock="None" JumpFlee="NO" MSPDToUsePos="0">
            <MoveList>
                <Frame Time="300" Dist="1.0799354" Angle="0.06966909" Accel="1" Height="0" MoveType="0" Gravity="600" JumpPower="300"/>
                <Frame Time="600" Dist="84.057198" Angle="0.0072418479" Accel="1" Height="0" MoveType="0" Gravity="600" JumpPower="300"/>
            </MoveList>
            <HitList>
                <Frame Type="SQUARE" Time="9999" HitCount="1" TermMin="0" TermMax="0" PosType="1" Dist="48.015636" RandDist="0" RandomPerHit="0" Angle="-3.0379868" Width="20" Length="60" AniTime="10199" RotAngle="0" ForceATK="0"/>
            </HitList>
            <EtcList>
                <Anim Time="0" Anim="skl" Speed="1"/>
                <Scp Scp="SKL_HIT_SQUARE_ADJUSTMENT" Client="NO" UseSleep="NO" Time="500">
                    <PosDist Angle="0" Dist="20"/>
                    <PosDist Angle="0" Dist="120"/>
                    <Num Num="20"/>
                    <Str Str="None"/>
                    <Str Str="None"/>
                    <Num Num="0"/>
                    <Num Num="0"/>
                    <Num Num="3"/>
                    <Num Num="0"/>
                    <Num Num="0"/>
                    <Num Num="0"/>
                    <Num Num="0"/>
                    <Num Num="0"/>
                    <Num Num="0"/>
                </Scp>
            </EtcList>
        </MainSkl>
    </Skill>
    <Skill Name="Mon_ep12_Wolf_Skill_1">
        <MainSkl ScrLock="None" JumpFlee="NO" MSPDToUsePos="0">
            <HitList>
                <Frame Type="FAN" Time="300" HitCount="1" TermMin="0" TermMax="0" PosType="0" Dist="0" RandDist="0" RandomPerHit="0" Angle="0" Width="30" Length="40" SklAngle="0.52359879" AniTime="500" RotAngle="0" ForceATK="0"/>
            </HitList>
            <EtcList>
                <Anim Time="0" Anim="atk" Speed="1"/>
            </EtcList>
        </MainSkl>
    </Skill>
    <Skill Name="Mon_ep12_Wolf_Skill_2">
        <MainSkl ScrLock="None" JumpFlee="NO" MSPDToUsePos="0">
            <MoveList>
                <Frame Time="300" Dist="1.0799354" Angle="0.06966909" Accel="1" Height="0" MoveType="0" Gravity="600" JumpPower="300"/>
                <Frame Time="600" Dist="46.251488" Angle="0.0049658595" Accel="1" Height="0" MoveType="0" Gravity="600" JumpPower="300"/>
            </MoveList>
            <HitList>
                <Frame Type="SQUARE" Time="9999" HitCount="1" TermMin="0" TermMax="0" PosType="0" Dist="0" RandDist="0" RandomPerHit="0" Angle="0" Width="10" Length="30" AniTime="10199" RotAngle="0" ForceATK="0"/>
            </HitList>
            <EtcList>
                <Anim Time="0" Anim="skl" Speed="1"/>
                <Scp Scp="SKL_HIT_SQUARE_ADJUSTMENT" Client="NO" UseSleep="NO" Time="500">
                    <PosDist Angle="0" Dist="10"/>
                    <PosDist Angle="0" Dist="60"/>
                    <Num Num="10"/>
                    <Str Str="None"/>
                    <Str Str="None"/>
                    <Num Num="0"/>
                    <Num Num="0"/>
                    <Num Num="3"/>
                    <Num Num="0"/>
                    <Num Num="0"/>
                    <Num Num="0"/>
                    <Num Num="0"/>
                    <Num Num="0"/>
                    <Num Num="0"/>
                </Scp>
            </EtcList>
        </MainSkl>
    </Skill>
    <Skill Name="Mon_ep12_Gari_Skill_1">
        <MainSkl ScrLock="None" JumpFlee="NO" MSPDToUsePos="0">
            <MoveList>
                <Frame Time="500" Dist="0.62239957" Angle="0.10068578" Accel="1" Height="0" MoveType="0" Gravity="600" JumpPower="300"/>
                <Frame Time="700" Dist="17.476191" Angle="0.0071953139" Accel="1" Height="0" MoveType="0" Gravity="600" JumpPower="300"/>
            </MoveList>
            <HitList>
                <Frame Type="FAN" Time="400" HitCount="1" TermMin="0" TermMax="0" PosType="0" Dist="0" RandDist="0" RandomPerHit="0" Angle="0" Width="30" Length="40" SklAngle="0.52359879" AniTime="600" RotAngle="0" ForceATK="0"/>
            </HitList>
            <EtcList>
                <Anim Time="0" Anim="atk" Speed="1"/>
            </EtcList>
        </MainSkl>
    </Skill>
    <Skill Name="Mon_ep12_Gari_Skill_2">
        <MainSkl ScrLock="None" JumpFlee="NO" MSPDToUsePos="0">
            <MoveList>
                <Frame Time="500" Dist="1.0799354" Angle="0.06966909" Accel="1" Height="0" MoveType="0" Gravity="600" JumpPower="300"/>
                <Frame Time="800" Dist="15.436668" Angle="-0.092805952" Accel="1" Height="0" MoveType="0" Gravity="600" JumpPower="300"/>
            </MoveList>
            <HitList>
                <Frame Type="SQUARE" Time="9999" HitCount="1" TermMin="0" TermMax="0" PosType="0" Dist="0" RandDist="0" RandomPerHit="0" Angle="0" Width="10" Length="40" AniTime="10199" RotAngle="0" ForceATK="0"/>
            </HitList>
            <EtcList>
                <Anim Time="0" Anim="skl" Speed="1"/>
                <Scp Scp="C_SOUND" Client="YES" UseSleep="NO" Time="0">
                    <Str Str="mon_jukopus_atk2_cast"/>
                </Scp>
                <Scp Scp="C_SOUND" Client="YES" UseSleep="NO" Time="300">
                    <Str Str="mon_jukopus_atk2_shot"/>
                </Scp>
                <Scp Scp="C_SOUND" Client="YES" UseSleep="NO" Time="350">
                    <Str Str="mon_mushroom_ent_atk1_cast"/>
                 </Scp>
                <Scp Scp="SKL_HIT_SQUARE_ADJUSTMENT" Client="NO" UseSleep="NO" Time="500">
                    <PosDist Angle="0" Dist="0"/>
                    <PosDist Angle="0" Dist="35"/>
                    <Num Num="12"/>
                    <Str Str="None"/>
                    <Str Str="None"/>
                    <Num Num="0"/>
                    <Num Num="1"/>
                    <Num Num="3"/>
                    <Num Num="0"/>
                    <Num Num="0"/>
                    <Num Num="0"/>
                    <Num Num="0"/>
                    <Num Num="0"/>
                    <Num Num="0"/>
                </Scp>
                <Scp Scp="SKL_HIT_SQUARE_ADJUSTMENT" Client="NO" UseSleep="NO" Time="650">
                    <PosDist Angle="0" Dist="0"/>
                    <PosDist Angle="0" Dist="35"/>
                    <Num Num="12"/>
                    <Str Str="None"/>
                    <Str Str="None"/>
                    <Num Num="0"/>
                    <Num Num="1"/>
                    <Num Num="3"/>
                    <Num Num="0"/>
                    <Num Num="0"/>
                    <Num Num="0"/>
                    <Num Num="0"/>
                    <Num Num="0"/>
                    <Num Num="0"/>
                </Scp>
                <Scp Scp="SKL_HIT_SQUARE_ADJUSTMENT" Client="NO" UseSleep="NO" Time="800">
                    <PosDist Angle="0" Dist="0"/>
                    <PosDist Angle="0" Dist="35"/>
                    <Num Num="12"/>
                    <Str Str="None"/>
                    <Str Str="None"/>
                    <Num Num="0"/>
                    <Num Num="1"/>
                    <Num Num="3"/>
                    <Num Num="0"/>
                    <Num Num="0"/>
                    <Num Num="0"/>
                    <Num Num="0"/>
                    <Num Num="0"/>
                    <Num Num="0"/>
                </Scp>
            </EtcList>
        </MainSkl>
    </Skill>
    <Skill Name="Mon_ep12_Neckko_Skill_1">
        <MainSkl ScrLock="None" JumpFlee="NO" MSPDToUsePos="0">
            <MoveList>
                <Frame Time="100" Dist="1.5200865" Angle="-1.4727049" Accel="1" Height="0" MoveType="0" Gravity="600" JumpPower="300"/>
                <Frame Time="400" Dist="55.595165" Angle="-0.032443296" Accel="1" Height="0" MoveType="0" Gravity="600" JumpPower="300"/>
            </MoveList>
            <HitList>
                <Frame Type="FAN" Time="9999" HitCount="1" TermMin="0" TermMax="0" PosType="0" Dist="0" RandDist="0" RandomPerHit="0" Angle="0" SklAngle="0.52359879" AniTime="10199" RotAngle="0" ForceATK="0"/>
            </HitList>
            <EtcList>
                <Anim Time="0" Anim="skl" Speed="1"/>
                <Scp Scp="EFT_AND_HIT_ARROW" Client="NO" UseSleep="YES" Time="0">
                    <Pos Angle="0" Dist="0"/>
                    <Pos Angle="0" Dist="80"/>
                    <Str_Arg Str="None" Arg="1"/>
                    <Num Num="25"/>
                    <Num Num="0.0099999998"/>
                    <Num Num="1"/>
                    <Num Num="0"/>
                    <Str_Arg Str="I_explosion002_green" Arg="1"/>
                    <Num Num="20"/>
                    <Num Num="100"/>
                    <Num Num="0"/>
                    <Num Num="20"/>
                    <Num Num="0.1"/>
                    <Num Num="1"/>
                    <Num Num="1000"/>
                    <Num Num="1"/>
                    <Num Num="0"/>
                    <Num Num="0"/>
                    <Num Num="100"/>
                </Scp>
            </EtcList>
        </MainSkl>
    </Skill>
    <Skill Name="Mon_ep12_Neckko_Skill_2">
        <MainSkl ScrLock="None" JumpFlee="NO" MSPDToUsePos="0">
            <HitList>
                <Frame Type="FAN" Time="500" HitCount="1" TermMin="0" TermMax="0" PosType="0" Dist="0" RandDist="0" RandomPerHit="0" Angle="0" Width="10" Length="45" SklAngle="0.52359879" AniTime="700" RotAngle="0" ForceATK="0"/>
            </HitList>
            <EtcList>
                <Anim Time="0" Anim="atk" Speed="1"/>
            </EtcList>
        </MainSkl>
    </Skill>
    <Skill Name="Mon_ep12_Poevita_Skill_1">
        <MainSkl ScrLock="None" JumpFlee="NO" MSPDToUsePos="0">
            <HitList>
                <Frame Type="FAN" Time="450" HitCount="1" TermMin="0" TermMax="0" PosType="0" Dist="0" RandDist="0" RandomPerHit="0" Angle="0" Width="30" Length="45" SklAngle="0.52359879" AniTime="650" RotAngle="0" ForceATK="0"/>
            </HitList>
            <EtcList>
                <Anim Time="0" Anim="atk" Speed="1"/>
            </EtcList>
        </MainSkl>
    </Skill>
    <Skill Name="Mon_ep12_Poevita_Skill_2">
        <MainSkl ScrLock="None" JumpFlee="NO" MSPDToUsePos="0">
            <MoveList>
                <Frame Time="600" Dist="1.0799354" Angle="0.06966909" Accel="1" Height="0" MoveType="0" Gravity="600" JumpPower="300"/>
                <Frame Time="800" Dist="28.350706" Angle="-0.012908929" Accel="1" Height="0" MoveType="0" Gravity="600" JumpPower="300"/>
            </MoveList>
            <HitList>
                <Frame Type="SQUARE" Time="600" HitCount="1" TermMin="0" TermMax="0" PosType="0" Dist="0" RandDist="0" RandomPerHit="0" Angle="0" Width="10" Length="50" AniTime="800" RotAngle="0" ForceATK="0"/>
            </HitList>
            <EtcList>
                <Anim Time="0" Anim="skl" Speed="1"/>
            </EtcList>
        </MainSkl>
    </Skill>
    <Skill Name="Mon_ep12_Sodininkas_Skill_1">
        <MainSkl ScrLock="None" JumpFlee="NO" MSPDToUsePos="0">
            <HitList>
                <Frame Type="FAN" Time="300" HitCount="1" TermMin="0" TermMax="0" PosType="0" Dist="0" RandDist="0" RandomPerHit="0" Angle="0" Width="30" Length="60" SklAngle="0.52359879" AniTime="500" RotAngle="0" ForceATK="0"/>
            </HitList>
            <EtcList>
                <Anim Time="0" Anim="atk" Speed="1"/>
            </EtcList>
        </MainSkl>
    </Skill>
    <Skill Name="Mon_ep12_Sodininkas_Skill_2">
        <MainSkl ScrLock="None" JumpFlee="NO" MSPDToUsePos="0">
            <HitList>
                <Frame Type="FAN" Time="300" HitCount="2" TermMin="500" TermMax="0" PosType="0" Dist="0" RandDist="0" RandomPerHit="0" Angle="0" Width="10" Length="55" SklAngle="0.34906587" AniTime="500" RotAngle="0" ForceATK="0"/>
            </HitList>
            <EtcList>
                <Anim Time="0" Anim="skl" Speed="1"/>
            </EtcList>
        </MainSkl>
    </Skill>
    <Skill Name="Mon_ep12_Tarnaite_Skill_1">
        <MainSkl ScrLock="None" JumpFlee="NO" MSPDToUsePos="0">
            <HitList>
                <Frame Type="FAN" Time="450" HitCount="1" TermMin="0" TermMax="0" PosType="0" Dist="0" RandDist="0" RandomPerHit="0" Angle="0" Width="30" Length="40" SklAngle="0.52359879" AniTime="650" RotAngle="0" ForceATK="0"/>
            </HitList>
            <EtcList>
                <Anim Time="0" Anim="atk" Speed="1"/>
            </EtcList>
        </MainSkl>
    </Skill>
    <Skill Name="Mon_ep12_Tarnaite_Skill_2">
        <MainSkl ScrLock="None" JumpFlee="NO" MSPDToUsePos="0">
            <HitList>
                <Frame Type="FAN" Time="500" HitCount="2" TermMin="600" TermMax="0" PosType="0" Dist="0" RandDist="0" RandomPerHit="0" Angle="0" Width="10" Length="80" SklAngle="0.52359879" AniTime="700" RotAngle="0" ForceATK="0"/>
            </HitList>
            <EtcList>
                <Anim Time="0" Anim="skl" Speed="1"/>
                <Scp Scp="C_EFFECT" Client="YES" UseSleep="NO" Time="500">
                    <Str_Arg Str="I_breath026_brown" Arg="3"/>
                    <Str Str="None"/>
                    <Num Num="1"/>
                </Scp>
            </EtcList>
        </MainSkl>
    </Skill>
    <Skill Name="Mon_ep12_Poana_Skill_1">
        <MainSkl ScrLock="None" JumpFlee="NO" MSPDToUsePos="0">
            <HitList>
                <Frame Type="SQUARE" Time="400" HitCount="1" TermMin="0" TermMax="0" PosType="0" Dist="0" RandDist="0" RandomPerHit="0" Angle="0" Width="10" Length="100" SklAngle="0.52359879" AniTime="600" RotAngle="0" ForceATK="1"/>
            </HitList>
            <EtcList>
                <Anim Time="0" Anim="atk" Speed="1"/>
                <Scp Scp="C_FORCE_EFT" Client="YES_Time" UseSleep="NO" Time="600">
                    <Str_Arg Str="I_wizard_meteorfall_force_dropfire_arts#Point_opal" Arg="0.5"/>
                    <Str Str="arrow_cast"/>
                    <Str_Arg Str="I_explosion002_green" Arg="1"/>
                    <Str Str="arrow_blow"/>
                    <Str Str="SLOW"/>
                    <Num Num="200"/>
                    <Num Num="1"/>
                    <Num Num="0"/>
                    <Angle_Abs Angle="0"/>
                    <Num Num="0"/>
                    <Num Num="0"/>
                    <Num Num="0"/>
                    <Num Num="0"/>
                    <Num Num="0"/>
                    <Num Num="0"/>
                    <Str Str="None"/>
                    <PosDist Angle="0" Dist="0"/>
                    <Num Num="0"/>
                </Scp>
            </EtcList>
        </MainSkl>
    </Skill>
    <Skill Name="Mon_ep12_Poana_Skill_2">
        <MainSkl ScrLock="None" JumpFlee="NO" MSPDToUsePos="0">
            <HitList>
                <Frame Type="SQUARE" Time="9999" HitCount="1" TermMin="0" TermMax="0" PosType="0" Dist="0" RandDist="0" RandomPerHit="0" Angle="0" Width="10" Length="40" AniTime="10199" RotAngle="0" ForceATK="0"/>
            </HitList>
            <EtcList>
                <Anim Time="0" Anim="skl" Speed="1"/>
                <Scp Scp="SKL_SET_TARGET_CIRCLE" Client="NO" UseSleep="NO" Time="0">
                    <Pos Angle="0" Dist="0"/>
                    <Num Num="100"/>
                    <Num Num="20"/>
                    <Num Num="2"/>
                    <Num Num="0"/>
                    <Num Num="1"/>
                    <Num Num="1"/>
                    <Num Num="0"/>
                    <Num Num="1"/>
                </Scp>
                <Scp Scp="EFT_AND_HIT" Client="NO" UseSleep="YES" TooltipScp="TOOLTIP_EFT_AND_HIT" Time="0">
                    <Pos Angle="0" Dist="0" PosType="9"/>
                    <Str_Arg Str="None" Arg="1"/>
                    <Num Num="1000"/>
                    <Str_Arg Str="F_burstup015_blue##1" Arg="1.5"/>
                    <Num Num="35"/>
                    <Num Num="100"/>
                    <Num Num="0"/>
                    <Num Num="2"/>
                    <Num Num="500"/>
                    <Str_Arg Str="None" Arg="1"/>
                    <Str Str="None"/>
                    <Num Num="1"/>
                    <Num Num="0"/>
                    <Num Num="0"/>
                </Scp>
                <Scp Scp="C_EFFECT" Client="YES" UseSleep="NO" Time="300">
                    <Str_Arg Str="I_smoke034_blue" Arg="2"/>
                    <Str Str="Point_opal"/>
                    <Num Num="0.69999999"/>
                </Scp>
            </EtcList>
        </MainSkl>
    </Skill>
    <Skill Name="Mon_ep12_Zima_Skill_1">
        <MainSkl ScrLock="None" JumpFlee="NO" MSPDToUsePos="0">
            <HitList>
                <Frame Type="FAN" Time="300" HitCount="1" TermMin="0" TermMax="0" PosType="0" Dist="0" RandDist="0" RandomPerHit="0" Angle="0" Width="30" Length="30" SklAngle="0.52359879" AniTime="500" RotAngle="0" ForceATK="0"/>
            </HitList>
            <EtcList>
                <Anim Time="0" Anim="atk" Speed="1"/>
            </EtcList>
        </MainSkl>
    </Skill>
    <Skill Name="Mon_ep12_Zima_Skill_2">
        <MainSkl ScrLock="None" JumpFlee="NO" MSPDToUsePos="0">
            <MoveList>
                <Frame Time="500" Dist="1.0799354" Angle="0.06966909" Accel="1" Height="0" MoveType="0" Gravity="600" JumpPower="300"/>
                <Frame Time="800" Dist="28.350706" Angle="-0.012908929" Accel="1" Height="0" MoveType="0" Gravity="600" JumpPower="300"/>
            </MoveList>
            <HitList>
                <Frame Type="SQUARE" Time="300" HitCount="1" TermMin="0" TermMax="0" PosType="0" Dist="0" RandDist="0" RandomPerHit="0" Angle="0" Width="10" Length="40" AniTime="500" RotAngle="0" ForceATK="0"/>
            </HitList>
            <EtcList>
                <Anim Time="0" Anim="skl" Speed="1"/>
                <Scp Scp="SKL_HIT_SQUARE_ADJUSTMENT" Client="NO" UseSleep="NO" Time="1500">
                    <PosDist Angle="0" Dist="0"/>
                    <PosDist Angle="0" Dist="35"/>
                    <Num Num="12"/>
                    <Str Str="None"/>
                    <Str Str="None"/>
                    <Num Num="0"/>
                    <Num Num="1"/>
                    <Num Num="3"/>
                    <Num Num="0"/>
                    <Num Num="0"/>
                    <Num Num="0"/>
                    <Num Num="0"/>
                    <Num Num="0"/>
                    <Num Num="0"/>
                </Scp>
            </EtcList>
        </MainSkl>
    </Skill>
    <Skill Name="Mon_ep12_Goblin_sword_rider_Skill_1">
        <MainSkl ScrLock="None" JumpFlee="NO" MSPDToUsePos="0">
            <HitList>
                <Frame Type="FAN" Time="250" HitCount="1" TermMin="0" TermMax="0" PosType="0" Dist="0" RandDist="0" RandomPerHit="0" Angle="0" Width="30" Length="50" SklAngle="0.34906587" AniTime="450" RotAngle="0" ForceATK="0"/>
            </HitList>
            <EtcList>
                <Anim Time="0" Anim="atk" Speed="1"/>
            </EtcList>
        </MainSkl>
    </Skill>
    <Skill Name="Mon_ep12_Goblin_sword_rider_Skill_2">
        <MainSkl ScrLock="None" JumpFlee="NO" MSPDToUsePos="0">
            <MoveList>
                <Frame Time="400" Dist="1.0799354" Angle="0.06966909" Accel="1" Height="0" MoveType="0" Gravity="600" JumpPower="300"/>
                <Frame Time="600" Dist="28.350706" Angle="-0.012908929" Accel="1" Height="0" MoveType="0" Gravity="600" JumpPower="300"/>
            </MoveList>
            <HitList>
                <Frame Type="FAN" Time="300" HitCount="1" TermMin="0" TermMax="0" PosType="0" Dist="0" RandDist="0" RandomPerHit="0" Angle="0" Width="10" Length="40" SklAngle="0.52359879" AniTime="500" RotAngle="-0.87266469" ForceATK="0"/>
                <Frame Type="FAN" Time="700" HitCount="1" TermMin="0" TermMax="0" PosType="0" Dist="0" RandDist="0" RandomPerHit="0" Angle="0" Width="10" Length="40" SklAngle="0.52359879" AniTime="900" RotAngle="0" ForceATK="0"/>
            </HitList>
            <EtcList>
                <Anim Time="0" Anim="skl" Speed="1"/>
            </EtcList>
        </MainSkl>
    </Skill>
    <Skill Name="Mon_ep12_Castle_beetle_Skill_1">
        <MainSkl ScrLock="None" JumpFlee="NO" MSPDToUsePos="0">
            <HitList>
                <Frame Type="FAN" Time="300" HitCount="1" TermMin="0" TermMax="0" PosType="0" Dist="0" RandDist="0" RandomPerHit="0" Angle="0" Width="30" Length="50" SklAngle="0.52359879" AniTime="500" RotAngle="0" ForceATK="0"/>
            </HitList>
            <EtcList>
                <Anim Time="0" Anim="atk" Speed="1"/>
            </EtcList>
        </MainSkl>
    </Skill>
    <Skill Name="Mon_ep12_Castle_beetle_Skill_2">
        <MainSkl ScrLock="None" JumpFlee="NO" MSPDToUsePos="0">
            <HitList>
                <Frame Type="FAN" Time="300" HitCount="1" TermMin="0" TermMax="0" PosType="0" Dist="0" RandDist="0" RandomPerHit="0" Angle="0" Width="10" Length="50" SklAngle="0.52359879" AniTime="500" RotAngle="0" ForceATK="0"/>
                <Frame Type="FAN" Time="400" HitCount="1" TermMin="0" TermMax="0" PosType="0" Dist="0" RandDist="0" RandomPerHit="0" Angle="0" Width="10" Length="50" SklAngle="0.52359879" AniTime="600" RotAngle="0" ForceATK="0"/>
                <Frame Type="FAN" Time="500" HitCount="1" TermMin="0" TermMax="0" PosType="0" Dist="0" RandDist="0" RandomPerHit="0" Angle="0" Width="10" Length="50" SklAngle="0.52359879" AniTime="700" RotAngle="0" ForceATK="0"/>
                <Frame Type="FAN" Time="600" HitCount="1" TermMin="0" TermMax="0" PosType="0" Dist="0" RandDist="0" RandomPerHit="0" Angle="0" Width="10" Length="50" SklAngle="0.52359879" AniTime="800" RotAngle="0" ForceATK="0"/>
                <Frame Type="FAN" Time="1200" HitCount="1" TermMin="0" TermMax="0" PosType="0" Dist="0" RandDist="0" RandomPerHit="0" Angle="0" Width="10" Length="50" SklAngle="0.52359879" AniTime="1400" RotAngle="0" ForceATK="0"/>
            </HitList>
            <EtcList>
                <Anim Time="0" Anim="skl" Speed="1"/>
            </EtcList>
        </MainSkl>
    </Skill>
</ToolSkill>
