<?xml version="1.0" encoding="UTF-8"?>
<!-- edited with XMLSPY v2004 rel. 3 U (http://www.xmlspy.com) by youngt616 (IMCGames Co., Ltd) -->
<!-- edited with XMLSpy v2008 sp1 (http://www.altova.com) by tachyon (EMBRACE) -->
<ActionDesc>
	<Sound frame="6.00" Value="2000" soundFile="skl_eff_atk_move_l_5"/>
	<Sound frame="12.00" Value="2000" soundFile="mon_voice_saltistter_2"/>
	<Sound frame="15.90" Value="2000" soundFile="skl_eff_stone_blow_m"/>
	<Shockwave frame="17" type="2" intensity="5" frequency="70" duration="0.3" range="1000"/>
	<Particle frame="17" attachActor="None" attachNode="Dummy_effect_skl1_cast_R" particleName="F_golem_atk2_hand" scale="7" pause="true" targetPos="false"/>
	<Shockwave frame="18" type="2" intensity="5" frequency="70" duration="0.3" range="1000"/>
	<Sound frame="27.00" Value="2000" soundFile="skl_eff_atk_move_l_4"/>
	<Sound frame="36.00" Value="2000" soundFile="skl_eff_stone_blow_m"/>
	<Shockwave frame="38" type="2" intensity="5" frequency="70" duration="0.3" range="1000"/>
	<Particle frame="38" attachActor="None" attachNode="Dummy_effect_skl1_cast_L" particleName="F_golem_atk2_hand" scale="7" pause="true" targetPos="false"/>
	<Shockwave frame="39" type="2" intensity="5" frequency="70" duration="0.3" range="1000"/>
</ActionDesc>
