<?xml version="1.0" encoding="UTF-8"?>
<!-- edited with XMLSPY v2004 rel. 3 U (http://www.xmlspy.com) by Shindongjin (IMCGames Co., Ltd) -->
<ActionDesc>
    <Sound frame="0.00" Value="5933" soundFile="skl_eff_atk_move_l_5"/>
    <Sound frame="3.00" Value="3748" soundFile="mon_voice_bird_7"/>
    <Particle frame="35" attachActor="None" attachNode="None" particleName="F_smoke033" hiddenObj="false" useAttach="true" scale="3" pause="true" targetPos="false"/>
    <Sound frame="69.00" Value="5933" soundFile="skl_eff_atk_move_s_10"/>
    <Sound frame="73.00" Value="5693" soundFile="skl_eff_body_atk_6"/>
    <Sound frame="81.00" Value="5933" soundFile="skl_eff_body_atk_7"/>
    <Sound frame="85.50" Value="5933" soundFile="skl_eff_atk_move_s_7"/>
    <Sound frame="88.00" Value="5933" soundFile="skl_eff_bite_s_1"/>
    <Sound frame="96.00" Value="5933" soundFile="skl_eff_atk_move_l_7"/>
    <Sound frame="120.00" Value="5933" soundFile="skl_eff_atk_move_l_3"/>
    <Sound frame="144.00" Value="5933" soundFile="mon_voice_bird_1"/>
</ActionDesc>
