<?xml version="1.0" encoding="UTF-8" ?>
<!-- edited with XMLSPY v2004 rel. 3 U (http://www.xmlspy.com) by might (IMCGames Co., Ltd) -->
<!-- edited with XMLSpy v2008 sp1 (http://www.altova.com) by tachyon (EMBRACE) -->
<ActionDesc>
    <Sound frame="0.00" Value="0" soundFile="m_treemonster_atk2" />
    <Particle frame="7" particleName="F_smoke066" attachNode="Dummy_emitter" scale="1.2" useAttach="true" pause="true" targetPos="false" />
    <Particle frame="7" particleName="F_smoke076" attachNode="Dummy_emitter" scale="1.2" useAttach="true" pause="true" targetPos="false" />
    <Particle frame="7" particleName="F_spark008_leaf" attachNode="Bip001 Ponytail2" scale="1.2" useAttach="true" pause="true" targetPos="false" />
    <Particle frame="7" particleName="F_spark008_leaf" attachNode="Bip001 Ponytail1" scale="1.2" useAttach="true" pause="true" targetPos="false" />
    <Sound frame="7" soundFile="skl_eff_stone_blow_m" />
    <HitAni frame="7.13" damratio="100" />
    <PostFix frame="10" ID="_height" />
    <PostFix frame="20" ID="_height" />
</ActionDesc>
