<?xml version="1.0" encoding="UTF-8"?>
<GameList>
    <Game Name="WHITETREES23_1_SQ04_MINI" minLv="0" maxLv="0" startWaitSec="0">
        <StageList>
            <Stage Name="SETUP">
                <ObjList>
                    <Obj Type="Monster" MonType="155142" Pos="-29.24#-11.61#1217.73" genCount="1" genTime="20000" objectKey="0" propList="&apos;RunMSPD&apos; &apos;60&apos; &apos;WlkMSPD&apos; &apos;48&apos; &apos;Name&apos; &apos;수수께끼의 사냥꾼&apos; ">
                        <SelfAI ActiveMessageMapInBattle="1">
                            <List>
                                <ToolScp Scp="S_AI_MOVE_RALLY" Client="NO" UseSleep="YES" ExtraArg="1">
                                    <AbsPos X="-555.95966" Y="11.362099" Z="1328.6459"/>
                                </ToolScp>
                                <ToolScp Scp="S_AI_MOVE_RALLY" Client="NO" UseSleep="YES" ExtraArg="1">
                                    <AbsPos X="-679.59906" Y="11.362099" Z="1150.0369"/>
                                </ToolScp>
                                <ToolScp Scp="S_AI_MOVE_RALLY" Client="NO" UseSleep="YES" ExtraArg="1">
                                    <AbsPos X="-919.992" Y="11.362099" Z="1270.0046"/>
                                </ToolScp>
                                <ToolScp Scp="S_AI_MOVE_RALLY" Client="NO" UseSleep="YES" ExtraArg="1">
                                    <AbsPos X="-970.62805" Y="11.362099" Z="1472.167"/>
                                </ToolScp>
                                <ToolScp Scp="SAI_FUNC2_DIRECT" Client="NO" UseSleep="NO">
                                    <Str Str="SCR_WHITETREES231_SQ_04_TURN"/>
                                </ToolScp>
                            </List>
                        </SelfAI>
                    </Obj>
                    <Obj Type="Trigger" triggerName="Trigger">
                        <Area>
                            <Pos Value="-508.413116 11.362099 1263.870239"/>
                            <Pos Value="-503.269104 11.362099 1332.558960"/>
                            <Pos Value="-461.774628 11.362099 1307.132080"/>
                            <Pos Value="-426.664124 11.362099 1296.401001"/>
                            <Pos Value="-399.048035 11.362099 1316.930176"/>
                            <Pos Value="-379.097534 11.362099 1317.830566"/>
                            <Pos Value="-381.948151 11.362098 1221.174316"/>
                            <Pos Value="-461.642853 11.362099 1259.885620"/>
                            <Pos Value="-508.973633 11.362099 1262.376465"/>
                        </Area>
                        <condScpList>
                            <ToolScp Scp="MGAME_TRG_COND_VALUE" Client="NO" UseSleep="NO">
                                <Str Str="white231_01"/>
                                <Str Str="=="/>
                                <Num Num="0"/>
                            </ToolScp>
                        </condScpList>
                        <enterScpList>
                            <ToolScp Scp="MGAME_TRG_START_STAGE" Client="NO" UseSleep="NO">
                                <Str Str="Wave1"/>
                            </ToolScp>
                            <ToolScp Scp="MGAME_TRG_MVALUE_ADD" Client="NO" UseSleep="NO">
                                <Str Str="white231_01"/>
                                <Num Num="1"/>
                            </ToolScp>
                        </enterScpList>
                    </Obj>
                    <Obj Type="Trigger" triggerName="Trigger">
                        <Area>
                            <Pos Value="-735.697876 11.362099 1331.405151"/>
                            <Pos Value="-669.958740 11.362099 1247.991699"/>
                            <Pos Value="-575.799927 11.362099 1178.403931"/>
                            <Pos Value="-576.122070 11.362099 1186.941895"/>
                            <Pos Value="-581.205139 11.362099 1221.622070"/>
                            <Pos Value="-579.292297 11.362099 1233.978882"/>
                            <Pos Value="-568.037964 11.362099 1245.716431"/>
                            <Pos Value="-647.414795 11.362099 1348.150024"/>
                            <Pos Value="-707.423218 11.362099 1350.289185"/>
                        </Area>
                        <condScpList>
                            <ToolScp Scp="MGAME_TRG_COND_VALUE" Client="NO" UseSleep="NO">
                                <Str Str="white231_02"/>
                                <Str Str="=="/>
                                <Num Num="0"/>
                            </ToolScp>
                        </condScpList>
                        <enterScpList>
                            <ToolScp Scp="MGAME_TRG_START_STAGE" Client="NO" UseSleep="NO">
                                <Str Str="Wave2"/>
                            </ToolScp>
                            <ToolScp Scp="MGAME_TRG_MVALUE_ADD" Client="NO" UseSleep="NO">
                                <Str Str="white231_02"/>
                                <Num Num="1"/>
                            </ToolScp>
                        </enterScpList>
                    </Obj>
                    <Obj Type="Trigger" triggerName="Trigger">
                        <Area>
                            <Pos Value="-834.609619 11.362099 1359.409058"/>
                            <Pos Value="-822.244934 11.362099 1278.803467"/>
                            <Pos Value="-878.792725 11.362099 1204.567749"/>
                            <Pos Value="-959.866943 11.362099 1166.317993"/>
                            <Pos Value="-999.226501 11.362099 1160.898804"/>
                            <Pos Value="-1035.658936 11.362099 1215.593140"/>
                            <Pos Value="-1050.132690 11.362099 1242.703613"/>
                            <Pos Value="-1044.150635 11.362099 1273.390503"/>
                            <Pos Value="-956.162598 11.362099 1292.880615"/>
                            <Pos Value="-921.558167 11.362099 1335.260864"/>
                            <Pos Value="-903.792053 11.362099 1408.710815"/>
                            <Pos Value="-897.290100 11.362099 1415.212646"/>
                        </Area>
                        <condScpList>
                            <ToolScp Scp="MGAME_TRG_COND_VALUE" Client="NO" UseSleep="NO">
                                <Str Str="white231_03"/>
                                <Str Str="=="/>
                                <Num Num="0"/>
                            </ToolScp>
                        </condScpList>
                        <enterScpList>
                            <ToolScp Scp="MGAME_TRG_START_STAGE" Client="NO" UseSleep="NO">
                                <Str Str="Wave3"/>
                            </ToolScp>
                            <ToolScp Scp="MGAME_TRG_MVALUE_ADD" Client="NO" UseSleep="NO">
                                <Str Str="white231_03"/>
                                <Num Num="1"/>
                            </ToolScp>
                        </enterScpList>
                    </Obj>
                </ObjList>
                <StageEvents>
                    <Event execCount="1" eventName="Setting">
                        <execList>
                            <ToolScp Scp="GAME_ST_EVT_EXEC_VALUE" Client="NO" UseSleep="NO">
                                <Str Str="white231_01"/>
                                <Num Num="0"/>
                            </ToolScp>
                            <ToolScp Scp="GAME_ST_EVT_EXEC_VALUE" Client="NO" UseSleep="NO">
                                <Str Str="white231_02"/>
                                <Num Num="0"/>
                            </ToolScp>
                            <ToolScp Scp="GAME_ST_EVT_EXEC_VALUE" Client="NO" UseSleep="NO">
                                <Str Str="white231_03"/>
                                <Num Num="0"/>
                            </ToolScp>
                        </execList>
                    </Event>
                    <Event execCount="1" eventName="Chat">
                        <execList>
                            <ToolScp Scp="MGAME_EVT_SCP_TO_MON" Client="NO" UseSleep="NO">
                                <MGameObj List="SETUP/0"/>
                                <Str Str="SCR_WHITETREES231_SQ_04_CHAT1"/>
                            </ToolScp>
                        </execList>
                    </Event>
                    <Event eventName="Clear">
                        <condList>
                            <ToolScp Scp="MGAME_EVT_COND_MONCNT" Client="NO" UseSleep="NO">
                                <MGameObj List="Wave1/0/Wave1/1/Wave1/2/Wave2/0/Wave2/1/Wave2/2/Wave2/3/Wave2/4/Wave2/5/Wave3/0/Wave3/1/Wave3/2"/>
                                <Num Num="0"/>
                            </ToolScp>
                            <ToolScp Scp="GAME_ST_EVT_COND_VALUE" Client="NO" UseSleep="NO">
                                <Str Str="white231_01"/>
                                <Str Str="=="/>
                                <Num Num="1"/>
                            </ToolScp>
                            <ToolScp Scp="GAME_ST_EVT_COND_VALUE" Client="NO" UseSleep="NO">
                                <Str Str="white231_02"/>
                                <Str Str="=="/>
                                <Num Num="1"/>
                            </ToolScp>
                            <ToolScp Scp="GAME_ST_EVT_COND_VALUE" Client="NO" UseSleep="NO">
                                <Str Str="white231_03"/>
                                <Str Str="=="/>
                                <Num Num="1"/>
                            </ToolScp>
                        </condList>
                        <execList>
                            <ToolScp Scp="GAME_ST_EVT_EXEC_STAGE_START" Client="NO" UseSleep="NO">
                                <Str Str="CLEAR"/>
                            </ToolScp>
                        </execList>
                    </Event>
                </StageEvents>
            </Stage>
            <Stage Name="Wave1" AutoStart="0">
                <ObjList>
                    <Obj Type="Monster" MonType="58547" Pos="-547.96#11.36#1363.34" genCount="1" maxStackCount="1" genTime="20000" objectKey="0" searchRange="100" tendency="1">
                        <SelfAI ActiveMessageMapInBattle="1">
                            <List>
                                <ToolScp Scp="S_AI_ATTACK_NEAR" Client="NO" UseSleep="NO">
                                    <Num Num="100"/>
                                </ToolScp>
                            </List>
                            <StartList>
                                <ToolScp Scp="S_AI_SET_TENDENCY" Client="NO" UseSleep="NO">
                                    <Str Str="Attack"/>
                                </ToolScp>
                            </StartList>
                        </SelfAI>
                    </Obj>
                    <Obj Type="Monster" MonType="58547" Pos="-588.60#11.36#1291.44" genCount="1" maxStackCount="1" genTime="20000" objectKey="1" searchRange="100" tendency="1">
                        <SelfAI ActiveMessageMapInBattle="1">
                            <List>
                                <ToolScp Scp="S_AI_ATTACK_NEAR" Client="NO" UseSleep="NO">
                                    <Num Num="100"/>
                                </ToolScp>
                            </List>
                            <StartList>
                                <ToolScp Scp="S_AI_SET_TENDENCY" Client="NO" UseSleep="NO">
                                    <Str Str="Attack"/>
                                </ToolScp>
                            </StartList>
                        </SelfAI>
                    </Obj>
                    <Obj Type="Monster" MonType="58547" Pos="-545.63#11.36#1261.57" genCount="1" maxStackCount="1" genTime="20000" objectKey="2" searchRange="100" tendency="1">
                        <SelfAI ActiveMessageMapInBattle="1">
                            <List>
                                <ToolScp Scp="S_AI_ATTACK_NEAR" Client="NO" UseSleep="NO">
                                    <Num Num="100"/>
                                </ToolScp>
                            </List>
                            <StartList>
                                <ToolScp Scp="S_AI_SET_TENDENCY" Client="NO" UseSleep="NO">
                                    <Str Str="Attack"/>
                                </ToolScp>
                            </StartList>
                        </SelfAI>
                    </Obj>
                </ObjList>
                <StageEvents>
                    <Event execCount="1" eventName="Chat">
                        <execList>
                            <ToolScp Scp="MGAME_EVT_SCP_TO_MON" Client="NO" UseSleep="NO">
                                <MGameObj List="SETUP/0"/>
                                <Str Str="SCR_WHITETREES231_SQ_04_CHAT2"/>
                            </ToolScp>
                        </execList>
                    </Event>
                </StageEvents>
            </Stage>
            <Stage Name="Wave2" AutoStart="0">
                <ObjList>
                    <Obj Type="Monster" MonType="58547" Pos="-584.23#11.36#1361.30" genCount="1" genTime="20000" objectKey="0" tendency="1">
                        <SelfAI ActiveMessageMapInBattle="1">
                            <List>
                                <ToolScp Scp="S_AI_ATTACK_NEAR" Client="NO" UseSleep="NO">
                                    <Num Num="200"/>
                                </ToolScp>
                            </List>
                            <StartList>
                                <ToolScp Scp="S_AI_SET_TENDENCY" Client="NO" UseSleep="NO">
                                    <Str Str="Attack"/>
                                </ToolScp>
                            </StartList>
                        </SelfAI>
                    </Obj>
                    <Obj Type="Monster" MonType="58547" Pos="-540.78#11.36#1297.86" genCount="1" genTime="20000" objectKey="1" tendency="1">
                        <SelfAI ActiveMessageMapInBattle="1">
                            <List>
                                <ToolScp Scp="S_AI_ATTACK_NEAR" Client="NO" UseSleep="NO">
                                    <Num Num="200"/>
                                </ToolScp>
                            </List>
                            <StartList>
                                <ToolScp Scp="S_AI_SET_TENDENCY" Client="NO" UseSleep="NO">
                                    <Str Str="Attack"/>
                                </ToolScp>
                            </StartList>
                        </SelfAI>
                    </Obj>
                    <Obj Type="Monster" MonType="58547" Pos="-762.05#11.36#1263.00" genCount="1" genTime="20000" objectKey="2" tendency="1">
                        <SelfAI ActiveMessageMapInBattle="1">
                            <List>
                                <ToolScp Scp="S_AI_ATTACK_NEAR" Client="NO" UseSleep="NO">
                                    <Num Num="200"/>
                                </ToolScp>
                            </List>
                            <StartList>
                                <ToolScp Scp="S_AI_SET_TENDENCY" Client="NO" UseSleep="NO">
                                    <Str Str="Attack"/>
                                </ToolScp>
                            </StartList>
                        </SelfAI>
                    </Obj>
                    <Obj Type="Monster" MonType="58548" Pos="-771.13#11.36#1178.08" genCount="1" genTime="20000" objectKey="3" tendency="1">
                        <SelfAI ActiveMessageMapInBattle="1">
                            <List>
                                <ToolScp Scp="S_AI_ATTACK_NEAR" Client="NO" UseSleep="NO">
                                    <Num Num="200"/>
                                </ToolScp>
                            </List>
                            <StartList>
                                <ToolScp Scp="S_AI_SET_TENDENCY" Client="NO" UseSleep="NO">
                                    <Str Str="Attack"/>
                                </ToolScp>
                            </StartList>
                        </SelfAI>
                    </Obj>
                    <Obj Type="Monster" MonType="58548" Pos="-694.92#11.36#1114.49" genCount="1" genTime="20000" objectKey="4" tendency="1">
                        <SelfAI ActiveMessageMapInBattle="1">
                            <List>
                                <ToolScp Scp="S_AI_ATTACK_NEAR" Client="NO" UseSleep="NO">
                                    <Num Num="200"/>
                                </ToolScp>
                            </List>
                            <StartList>
                                <ToolScp Scp="S_AI_SET_TENDENCY" Client="NO" UseSleep="NO">
                                    <Str Str="Attack"/>
                                </ToolScp>
                            </StartList>
                        </SelfAI>
                    </Obj>
                    <Obj Type="Monster" MonType="58547" Pos="-597.17#11.36#1105.45" genCount="1" genTime="20000" objectKey="5" tendency="1">
                        <SelfAI ActiveMessageMapInBattle="1">
                            <List>
                                <ToolScp Scp="S_AI_ATTACK_NEAR" Client="NO" UseSleep="NO">
                                    <Num Num="200"/>
                                </ToolScp>
                            </List>
                            <StartList>
                                <ToolScp Scp="S_AI_SET_TENDENCY" Client="NO" UseSleep="NO">
                                    <Str Str="Attack"/>
                                </ToolScp>
                            </StartList>
                        </SelfAI>
                    </Obj>
                </ObjList>
            </Stage>
            <Stage Name="Wave3" AutoStart="0">
                <ObjList>
                    <Obj Type="Monster" MonType="58548" Pos="-852.93#11.36#1120.41" genCount="1" genTime="20000" objectKey="0" tendency="1">
                        <SelfAI ActiveMessageMapInBattle="1">
                            <List>
                                <ToolScp Scp="S_AI_ATTACK_NEAR" Client="NO" UseSleep="NO">
                                    <Num Num="200"/>
                                </ToolScp>
                            </List>
                            <StartList>
                                <ToolScp Scp="S_AI_SET_TENDENCY" Client="NO" UseSleep="NO">
                                    <Str Str="Attack"/>
                                </ToolScp>
                            </StartList>
                        </SelfAI>
                    </Obj>
                    <Obj Type="Monster" MonType="58548" Pos="-787.87#11.36#1183.69" genCount="1" genTime="20000" objectKey="1" tendency="1">
                        <SelfAI ActiveMessageMapInBattle="1">
                            <List>
                                <ToolScp Scp="S_AI_ATTACK_NEAR" Client="NO" UseSleep="NO">
                                    <Num Num="200"/>
                                </ToolScp>
                            </List>
                            <StartList>
                                <ToolScp Scp="S_AI_SET_TENDENCY" Client="NO" UseSleep="NO">
                                    <Str Str="Attack"/>
                                </ToolScp>
                            </StartList>
                        </SelfAI>
                    </Obj>
                    <Obj Type="Monster" MonType="58548" Pos="-788.74#11.36#1283.21" genCount="1" genTime="20000" objectKey="2" tendency="1">
                        <SelfAI ActiveMessageMapInBattle="1">
                            <List>
                                <ToolScp Scp="S_AI_ATTACK_NEAR" Client="NO" UseSleep="NO">
                                    <Num Num="200"/>
                                </ToolScp>
                            </List>
                            <StartList>
                                <ToolScp Scp="S_AI_SET_TENDENCY" Client="NO" UseSleep="NO">
                                    <Str Str="Attack"/>
                                </ToolScp>
                            </StartList>
                        </SelfAI>
                    </Obj>
                </ObjList>
                <StageEvents>
                    <Event execCount="1" eventName="Chat">
                        <execList>
                            <ToolScp Scp="MGAME_EVT_SCP_TO_MON" Client="NO" UseSleep="NO">
                                <MGameObj List="SETUP/0"/>
                                <Str Str="SCR_WHITETREES231_SQ_04_CHAT3"/>
                            </ToolScp>
                        </execList>
                    </Event>
                </StageEvents>
            </Stage>
            <Stage Name="CLEAR" AutoStart="0">
                <ObjList/>
                <StageEvents>
                    <Event execCount="1" eventName="Chat">
                        <execList>
                            <ToolScp Scp="MGAME_EVT_SCP_TO_MON" Client="NO" UseSleep="NO">
                                <MGameObj List="SETUP/0"/>
                                <Str Str="SCR_WHITETREES231_SQ_04_CHAT4"/>
                            </ToolScp>
                        </execList>
                    </Event>
                    <Event eventName="End">
                        <condList>
                            <ToolScp Scp="GAME_ST_EVT_COND_TIMECHECK" Client="NO" UseSleep="NO">
                                <Num Num="5"/>
                            </ToolScp>
                        </condList>
                        <execList>
                            <ToolScp Scp="MGAME_EXEC_SSN_ADD" Client="NO" UseSleep="NO">
                                <Str Str="SSN_WHITETREES23_1_SQ04"/>
                                <Str Str="QuestInfoValue1"/>
                                <Num Num="1"/>
                            </ToolScp>
                            <ToolScp Scp="MGAME_END" Client="NO" UseSleep="NO">
                                <Num Num="1"/>
                            </ToolScp>
                        </execList>
                    </Event>
                </StageEvents>
            </Stage>
        </StageList>
    </Game>
</GameList>
