<?xml version="1.0" encoding="UTF-8"?><!-- edited with XMLSPY v2004 rel. 3 U (http://www.xmlspy.com) by Shindongjin (IMCGames Co., Ltd) --><ActionDesc>	<Particle frame="0" particleName="F_smoke109" attachNode="Dummy_top" scale="1" useAttach="true"/>	<Particle frame="2" particleName="F_smoke109" attachNode="Dummy_top" scale="1" useAttach="true"/>	<Particle frame="4" particleName="F_smoke109" attachNode="Dummy_top" scale="1" useAttach="true"/>	<Particle frame="6" particleName="F_smoke109" attachNode="Dummy_top" scale="2" useAttach="true"/>	<Particle frame="8" particleName="F_smoke109" attachNode="Dummy_top" scale="2" useAttach="true"/>	<Particle frame="10" particleName="F_smoke109" attachNode="Dummy_top" scale="2" useAttach="true"/>	<Particle frame="12" particleName="F_smoke109" attachNode="Dummy_top" scale="2" useAttach="true"/>	<Particle frame="14" particleName="F_smoke109" attachNode="Dummy_top" scale="3" useAttach="true"/>	<Particle frame="16" particleName="F_smoke109" attachNode="Dummy_top" scale="3" useAttach="true"/>	<Particle frame="18" particleName="F_smoke109" attachNode="Dummy_top" scale="3" useAttach="true"/>	<Particle frame="20" particleName="F_smoke109" attachNode="Dummy_top" scale="3" useAttach="true"/></ActionDesc>